{
  "parent": "minecraft:item/handheld",
  "overrides": [
    {
      "model": "magical_relics:item/sword1",
      "predicate": {
        "magical_relics:sword_variant": 1.0
      }
    },
    {
      "model": "magical_relics:item/sword2",
      "predicate": {
        "magical_relics:sword_variant": 2.0
      }
    },
    {
      "model": "magical_relics:item/sword3",
      "predicate": {
        "magical_relics:sword_variant": 3.0
      }
    },
    {
      "model": "magical_relics:item/sword4",
      "predicate": {
        "magical_relics:sword_variant": 4.0
      }
    },
    {
      "model": "magical_relics:item/sword5",
      "predicate": {
        "magical_relics:sword_variant": 5.0
      }
    },
    {
      "model": "magical_relics:item/sword6",
      "predicate": {
        "magical_relics:sword_variant": 6.0
      }
    },
    {
      "model": "magical_relics:item/sword7",
      "predicate": {
        "magical_relics:sword_variant": 7.0
      }
    },
    {
      "model": "magical_relics:item/sword8",
      "predicate": {
        "magical_relics:sword_variant": 8.0
      }
    },
    {
      "model": "magical_relics:item/sword9",
      "predicate": {
        "magical_relics:sword_variant": 9.0
      }
    },
    {
      "model": "magical_relics:item/sword10",
      "predicate": {
        "magical_relics:sword_variant": 10.0
      }
    },
    {
      "model": "magical_relics:item/sword11",
      "predicate": {
        "magical_relics:sword_variant": 11.0
      }
    },
    {
      "model": "magical_relics:item/sword12",
      "predicate": {
        "magical_relics:sword_variant": 12.0
      }
    },
    {
      "model": "magical_relics:item/sword13",
      "predicate": {
        "magical_relics:sword_variant": 13.0
      }
    },
    {
      "model": "magical_relics:item/sword14",
      "predicate": {
        "magical_relics:sword_variant": 14.0
      }
    },
    {
      "model": "magical_relics:item/sword15",
      "predicate": {
        "magical_relics:sword_variant": 15.0
      }
    }
  ],
  "textures": {
    "layer0": "magical_relics:item/sword/sword1"
  }
}